{"jobs":[{"completedAt":"2025-11-09T11:45:20Z","conclusion":"success","databaseId":54905876609,"name":"deploy","startedAt":"2025-11-09T11:42:44Z","status":"completed","steps":[{"completedAt":"2025-11-09T11:42:47Z","conclusion":"success","name":"Set up job","number":1,"startedAt":"2025-11-09T11:42:45Z","status":"completed"},{"completedAt":"2025-11-09T11:42:48Z","conclusion":"success","name":"Run actions/checkout@v4","number":2,"startedAt":"2025-11-09T11:42:47Z","status":"completed"},{"completedAt":"2025-11-09T11:42:48Z","conclusion":"success","name":"Generate build metadata","number":3,"startedAt":"2025-11-09T11:42:48Z","status":"completed"},{"completedAt":"2025-11-09T11:42:49Z","conclusion":"success","name":"Preflight context (names only)","number":4,"startedAt":"2025-11-09T11:42:48Z","status":"completed"},{"completedAt":"2025-11-09T11:42:49Z","conclusion":"success","name":"Sanity check secret parse (no output)","number":5,"startedAt":"2025-11-09T11:42:49Z","status":"completed"},{"completedAt":"2025-11-09T11:42:49Z","conclusion":"success","name":"Authenticate to Google Cloud","number":6,"startedAt":"2025-11-09T11:42:49Z","status":"completed"},{"completedAt":"2025-11-09T11:43:18Z","conclusion":"success","name":"Set up Cloud SDK","number":7,"startedAt":"2025-11-09T11:42:49Z","status":"completed"},{"completedAt":"2025-11-09T11:43:20Z","conclusion":"success","name":"Ensure required Google APIs are enabled","number":8,"startedAt":"2025-11-09T11:43:18Z","status":"completed"},{"completedAt":"2025-11-09T11:43:21Z","conclusion":"success","name":"Ensure Artifact Registry auth","number":9,"startedAt":"2025-11-09T11:43:20Z","status":"completed"},{"completedAt":"2025-11-09T11:45:05Z","conclusion":"success","name":"Deploy via Cloud Build and Cloud Run","number":10,"startedAt":"2025-11-09T11:43:21Z","status":"completed"},{"completedAt":"2025-11-09T11:45:15Z","conclusion":"success","name":"Ensure env on service","number":11,"startedAt":"2025-11-09T11:45:05Z","status":"completed"},{"completedAt":"2025-11-09T11:45:15Z","conclusion":"success","name":"Adapter preflight","number":12,"startedAt":"2025-11-09T11:45:15Z","status":"completed"},{"completedAt":"2025-11-09T11:45:15Z","conclusion":"success","name":"Post Authenticate to Google Cloud","number":23,"startedAt":"2025-11-09T11:45:15Z","status":"completed"},{"completedAt":"2025-11-09T11:45:16Z","conclusion":"success","name":"Post Run actions/checkout@v4","number":24,"startedAt":"2025-11-09T11:45:15Z","status":"completed"},{"completedAt":"2025-11-09T11:45:16Z","conclusion":"success","name":"Complete job","number":25,"startedAt":"2025-11-09T11:45:16Z","status":"completed"}],"url":"https://github.com/Global-investment-Consulting/Vida/actions/runs/19207934627/job/54905876609"}]}
